LICENSE.txt
README.md
setup.cfg
setup.py
Topsis_Abhav_102016096/__init__.py
Topsis_Abhav_102016096/topsis.py
Topsis_Abhav_102016096.egg-info/PKG-INFO
Topsis_Abhav_102016096.egg-info/SOURCES.txt
Topsis_Abhav_102016096.egg-info/dependency_links.txt
Topsis_Abhav_102016096.egg-info/requires.txt
Topsis_Abhav_102016096.egg-info/top_level.txt